jupyter_kernels/__init__.py
jupyter_kernels/__main__.py
jupyter_kernels/__version__.py
jupyter_kernels/application.py
jupyter_kernels/serverapplication.py
jupyter_kernels/handlers/__init__.py
jupyter_kernels/handlers/base.py
jupyter_kernels/handlers/config/__init__.py
jupyter_kernels/handlers/config/handler.py
jupyter_kernels/handlers/content/__init__.py
jupyter_kernels/handlers/content/handler.py
jupyter_kernels/handlers/index/__init__.py
jupyter_kernels/handlers/index/handler.py
jupyter_kernels/handlers/jump/__init__.py
jupyter_kernels/handlers/jump/handler.py
jupyter_kernels/static/README.md
jupyter_kernels/templates/index.html
jupyter_kernels/tests/__init__.py
jupyter_kernels/tests/test_handlers.py
jupyter_kernels-1.2.20.data/data/etc/jupyter/jupyter_notebook_config.d/jupyter_kernels.json
jupyter_kernels-1.2.20.data/data/etc/jupyter/jupyter_server_config.d/jupyter_kernels.json
jupyter_kernels-1.2.20.dist-info/METADATA
jupyter_kernels-1.2.20.dist-info/WHEEL
jupyter_kernels-1.2.20.dist-info/entry_points.txt
jupyter_kernels-1.2.20.dist-info/licenses/LICENSE
jupyter_kernels-1.2.20.dist-info/RECORD
